get_passphrase/__init__.py
get_passphrase/__main__.py
get_passphrase/basic.py
get_passphrase/passphrase.py
get_passphrase/resolver.py
get_passphrase/resolvers/__init__.py
get_passphrase/resolvers/any_resolver.py
get_passphrase/resolvers/empty_resolver.py
get_passphrase/resolvers/env_resolver.py
get_passphrase/resolvers/fd_resolver.py
get_passphrase/resolvers/file_resolver.py
get_passphrase/resolvers/fixed_resolver.py
get_passphrase/resolvers/getpass_resolver.py
get_passphrase/resolvers/inline_resolver.py
get_passphrase/resolvers/keyring_resolver.py
get_passphrase/resolvers/none_resolver.py
get_passphrase/resolvers/standard_resolvers.py
get_passphrase/resolvers/stdin_resolver.py
get_passphrase/typehints.py
get_passphrase/util.py
get_passphrase-1.0.0.dist-info/entry_points.txt
get_passphrase-1.0.0.dist-info/LICENSE
get_passphrase-1.0.0.dist-info/WHEEL
get_passphrase-1.0.0.dist-info/METADATA
get_passphrase-1.0.0.dist-info/RECORD
