Metadata-Version: 2.1
Name: get-passphrase
Version: 1.0.0
Summary: Extensible passphrase resolver, supporting prompting as well as passphrases stored in environment variables, files or keychains
Home-page: https://github.com/sammck/get-passphrase
License: MIT
Keywords: password,passphrase,secret,keychain,keyring
Author: Sam McKelvie
Author-email: dev@mckelvie.org
Requires-Python: >=3.8,<4.0
Classifier: License :: OSI Approved :: MIT License
Classifier: Programming Language :: Python :: 3
Classifier: Programming Language :: Python :: 3.10
Classifier: Programming Language :: Python :: 3.8
Classifier: Programming Language :: Python :: 3.9
Requires-Dist: keyring (>=23.5.0,<24.0.0)
Requires-Dist: sentinel (>=0.3.0,<0.4.0)
Project-URL: Repository, https://github.com/sammck/get-passphrase.git
